django_cas/__init__.py
django_cas/apps.py
django_cas/backends.py
django_cas/decorators.py
django_cas/exceptions.py
django_cas/middleware.py
django_cas/models.py
django_cas/urls.py
django_cas/utils.py
django_cas/views.py
django_cas/management/__init__.py
django_cas/management/commands/__init__.py
django_cas/management/commands/clearcassessions.py
django_cas/migrations/0001_initial.py
django_cas/migrations/__init__.py
django_cas/tests/cas_tests.py
django_cas/tests/get_pgt.py
tests/__init__.py
tests/test_clearsessions.py
tests/test_middleware.py
tests/test_settings.py
tests/urls.py
tests/views.py
django_cas_sso-1.2.7.dist-info/METADATA
django_cas_sso-1.2.7.dist-info/WHEEL
django_cas_sso-1.2.7.dist-info/top_level.txt
django_cas_sso-1.2.7.dist-info/zip-safe
django_cas_sso-1.2.7.dist-info/RECORD
