Metadata-Version: 2.1
Name: django-cas-sso
Version: 1.2.7
Summary: Django Cas SSO Client (inherited from django-cas)
Home-page: http://github.com/unistra/django-cas/
Author: di-dip-unistra
Author-email: di-dip@unistra.fr
Maintainer: di-dip-unistra
Maintainer-email: di-dip@unistra.fr
License: MIT
Download-URL: http://pypi.python.org/pypi/django-cas-sso
Keywords: django,cas,sso
Platform: UNKNOWN
Classifier: Development Status :: 5 - Production/Stable
Classifier: Environment :: Console
Classifier: Intended Audience :: End Users/Desktop
Classifier: Natural Language :: English
Classifier: Operating System :: OS Independent
Classifier: Programming Language :: Python
Classifier: Topic :: Internet :: WWW/HTTP :: Dynamic Content :: CGI Tools/Libraries
Classifier: Topic :: Utilities
Classifier: License :: OSI Approved :: BSD License
Requires-Dist: six
